LogpPredictor.py
LogpPredictor_CGenFF.py
LogpPredictor_MMFF94.py
classicalgsg/__init__.py
classicalgsg/classicalgsg.py
classicalgsg/atomic_attr/__init__.py
classicalgsg/atomic_attr/molecularff.py
classicalgsg/atomic_attr/openchem.py
classicalgsg/atomic_attr/utils.py
classicalgsg/atomic_attr/forcefields_params/cgenff_AC36.dat
classicalgsg/atomic_attr/forcefields_params/gaff.dat
classicalgsg/atomic_attr/forcefields_params/gaff2.dat
classicalgsg/atomic_attr/forcefields_params/gaff2_AC31.dat
classicalgsg/atomic_attr/forcefields_params/gaff2_lj.dat
classicalgsg/atomic_attr/forcefields_params/gaff_AC31.dat
classicalgsg/atomic_attr/forcefields_params/ghemical.prm
classicalgsg/atomic_attr/forcefields_params/mmff.dat
classicalgsg/atomic_attr/forcefields_params/mmffvdw.par
classicalgsg/atomic_attr/forcefields_params/par_all36_cgenff.prm
classicalgsg/atomic_attr/forcefields_params/process.py
classicalgsg/atomic_attr/forcefields_params/scan.py
classicalgsg/atomic_attr/forcefields_params/uff.prm
classicalgsg/atomic_attr/forcefields_params/uff_AC26.dat
classicalgsg/formats/cgenff_mol2str.sh
classicalgsg/formats/copy_failed.py
classicalgsg/formats/draw.py
classicalgsg/formats/gaff_pdb2mol.sh
classicalgsg/formats/mol2pdb_rdkit.py
classicalgsg/formats/ms_convert_smiles.sh
classicalgsg/formats/ms_mol2pdb.sh
classicalgsg/formats/openbabel_utils.py
classicalgsg/formats/processSDF.py
classicalgsg/formats/process_sd.py
classicalgsg/formats/rdkit_utils.py
classicalgsg/formats/schrodinger_mol2pdb.sh
classicalgsg/molreps_models/__init__.py
classicalgsg/molreps_models/gsg.py
classicalgsg/molreps_models/utils.py
classicalgsg/nn_models/__init__.py
classicalgsg/nn_models/dataloader.py
classicalgsg/nn_models/datasetbuilder.py
classicalgsg/nn_models/evalmetrics.py
classicalgsg/nn_models/graphdataset.py
classicalgsg/nn_models/models.py
classicalgsg/nn_models/reporter.py
classicalgsg/nn_models/test.py
classicalgsg/pretrained_models/model_4_zfs.pt
classicalgsg-0.0.1a0.dev3.dist-info/LICENSE
classicalgsg-0.0.1a0.dev3.dist-info/METADATA
classicalgsg-0.0.1a0.dev3.dist-info/WHEEL
classicalgsg-0.0.1a0.dev3.dist-info/top_level.txt
classicalgsg-0.0.1a0.dev3.dist-info/RECORD
