Metadata-Version: 2.1
Name: classicalgsg
Version: 0.0.1a0.dev3
Summary: ClassicalGSG
Home-page: https://github.com/ADicksonLab/ClassicalGSG
Author: Nazanin Donyapour
Author-email: nazanin@msu.edu
License: MIT
Platform: UNKNOWN
Classifier: Topic :: Utilities
Classifier: License :: OSI Approved :: MIT License
Classifier: Programming Language :: Python :: 3
Requires-Dist: numpy
Requires-Dist: pandas
Requires-Dist: scikit-learn
Requires-Dist: skorch
Requires-Dist: tabulate
Requires-Dist: ParmEd
